{
  "welcome": "Welcome",
  "rememberMe": "Remember me",
  "headerHome": "Home",
  "headerProfile": "Profile",
  "headerPhotoList": "Photo List",
  "headerProducts": "Products",
  "headerLogout": "Logout",
  "email": "Email address",
  "emailRequire": "Please fill in your Email ",
  "emailInvalid": "Email is not valid",
  "password": "Password",
  "passwordRequire": "Please fill in your password",
  "minPasswordInvalid": "Password is at least 6 character",
  "repeatPassword": "Repeat password",
  "repeatPasswordNotMatch": "Reapeat password not match",
  "name": "Name",
  "nameRequire": "Please fill in your name",
  "minNameInvalid": "Name is at least 6 character",
  "gender": "Gender",
  "genderRequire": "Please select your gender",
  "region": "Region",
  "regionRequire": "Please select your region",
  "state": "City",
  "stateRequire": "Please select your city",
  "male": "Male",
  "female": "Female",
  "login": "Login",
  "register": "Sign up",
  "registerSuccess": "Sign up success",
  "openOptions": "Select a option",
  "applyFilter": "Apply",
  "clearFilter": "Clear",
  "close": "Close",
  "remove": "Remove",
  "stopChange": "Close",
  "saveChange": "Save changes",
  "profileAvatarHover": "Change your avatar",
  "changeAvatarTitle": "Change avatar",
  "changeAvatarPreview": "Preview",
  "payrollTransistionTitle": "Pay-roll transitions list",
  "fromDate": "From",
  "toDate": "To",
  "paginationFirst": "First",
  "paginationLast": "Last",
  "exportCSV": "Export CSV",
  "productStatus": "Status",
  "productDate": "Date",
  "productCurrency": "Currency",
  "productTotal": "Total",
  "productOrder": "Order",
  "viewDetailProduct": "View Detail",
  "productDetailTitle": "Product Detail",
  "removingProductAlertTitle": "Removing Product",
  "selectProductsPerPage": "Products per page",
  "countProductShow": "Showing from",
  "countProductTo": "to",
  "countProductOf": "of"
}